[
    {
        "id": 0,
        "question": "Are you a Greek citizen?",
        "options":["Yes","No"]
    },
    {
        "id": 1,
        "question": "Are you a permenant resident in Greece?",
        "options":["Yes","No"]
    },
    {
        "id": 2,
        "question": "Are you registered in a municipality in Greece?",
        "options":["Yes","No"]
    },
    {
        "id": 3,
        "question": "Have you been married in a country outside of Greece?",
        "options":["Yes","No"]
    },
    {
        "id": 4,
        "question": "Is your marriage certificate recognised in Greece?",
        "options":["Yes","No"]
    },
    {
        "id": 5,
        "question": "Is you marriage certificate officially translated?",
        "options":["Yes","No"]
    },
    {
        "id": 6,
        "question": "Who is submiting the request of transcript?",
        "options":["The spouces","Relatives", "Third Person / Νon-obligated person"]
    }
]
